Metadata-Version: 2.1
Name: turtlepolish
Version: 1.0.0
Summary: This is turtle graphic library in Polish commands.
Home-page: 
Author: DaytimeSpore380
Author-email: michal.jakubiuk11@gmail.com
License: MIT
Keywords: turtle polish
Classifier: Development Status :: 5 - Production/Stable
Classifier: Intended Audience :: Education
Classifier: Operating System :: Microsoft :: Windows :: Windows 10
Classifier: License :: OSI Approved :: MIT License
Classifier: Programming Language :: Python :: 3
License-File: LICENSE.txt
